nvidia/libcal/cu12/include/cal.h
nvidia/libcal/cu12/include/ucc/api/ucc.h
nvidia/libcal/cu12/include/ucc/api/ucc_def.h
nvidia/libcal/cu12/include/ucc/api/ucc_status.h
nvidia/libcal/cu12/include/ucc/api/ucc_version.h
nvidia/libcal/cu12/lib/libcal.so.0
nvidia/libcal/cu12/lib/libucc.so.1
nvidia/libcal/cu12/lib/ucc/libucc_cl_basic.so
nvidia/libcal/cu12/lib/ucc/libucc_cl_hier.so
nvidia/libcal/cu12/lib/ucc/libucc_ec_cpu.so
nvidia/libcal/cu12/lib/ucc/libucc_ec_cuda.so
nvidia/libcal/cu12/lib/ucc/libucc_mc_cpu.so
nvidia/libcal/cu12/lib/ucc/libucc_mc_cuda.so
nvidia/libcal/cu12/lib/ucc/libucc_tl_cuda.so
nvidia/libcal/cu12/lib/ucc/libucc_tl_mlx5.so
nvidia/libcal/cu12/lib/ucc/libucc_tl_nccl.so
nvidia/libcal/cu12/lib/ucc/libucc_tl_self.so
nvidia/libcal/cu12/lib/ucc/libucc_tl_sharp.so
nvidia/libcal/cu12/lib/ucc/libucc_tl_shm.so
nvidia/libcal/cu12/lib/ucc/libucc_tl_ucp.so
nvidia/libcal/cu12/share/ucc.conf
nvidia_libcal_cu12-0.4.4.50.post1.dist-info/LICENSE
nvidia_libcal_cu12-0.4.4.50.post1.dist-info/METADATA
nvidia_libcal_cu12-0.4.4.50.post1.dist-info/WHEEL
nvidia_libcal_cu12-0.4.4.50.post1.dist-info/top_level.txt
nvidia_libcal_cu12-0.4.4.50.post1.dist-info/RECORD
