Metadata-Version: 2.1
Name: nvidia-libcal-cu12
Version: 0.4.4.50.post1
Summary: NVIDIA libcal - Communication Abstraction Library
Author-email: Nvidia CUDA Installer Team <cuda_installer@nvidia.com>
License: LICENSE AGREEMENT FOR NVIDIA MATH LIBRARIES SOFTWARE DEVELOPMENT KITS
Project-URL: Homepage, https://docs.nvidia.com/cuda/cublasmp/usage/cal.html
Project-URL: Documentation, https://docs.nvidia.com/cuda/cublasmp/usage/cal.html
Keywords: nvidia,math libraries,ucc,multi-node,multi-gpu,mgmn
Classifier: Development Status :: 5 - Production/Stable
Classifier: Environment :: GPU :: NVIDIA CUDA
Classifier: Environment :: GPU :: NVIDIA CUDA :: 12
Classifier: Intended Audience :: Developers
Classifier: Intended Audience :: Education
Classifier: Intended Audience :: Science/Research
Classifier: License :: Other/Proprietary License
Classifier: Natural Language :: English
Classifier: Operating System :: POSIX :: Linux
Classifier: Programming Language :: C
Classifier: Programming Language :: C++
Classifier: Topic :: Scientific/Engineering
Classifier: Topic :: Software Development
Classifier: Topic :: Software Development :: Libraries
License-File: LICENSE
Requires-Dist: libucx-cu12
Provides-Extra: nccl
Requires-Dist: nvidia-nccl-cu12; extra == "nccl"
